sam/__init__.py
sam/__main__.py
sam/sam.py
telexy.sam-1.23.931.dist-info/LICENSE.txt
telexy.sam-1.23.931.dist-info/METADATA
telexy.sam-1.23.931.dist-info/WHEEL
telexy.sam-1.23.931.dist-info/top_level.txt
telexy.sam-1.23.931.dist-info/RECORD
