Metadata-Version: 2.1
Name: telexy.sam
Version: 1.23.931
Summary: SAM Inference service
Author: Telexy
Author-email: support@telexy.com
Classifier: Programming Language :: Python :: 3
Classifier: License :: OSI Approved :: MIT License
Classifier: Operating System :: OS Independent
Requires-Python: >=3.10
License-File: LICENSE.txt
Requires-Dist: telexy.mars
Requires-Dist: opencv-python
Requires-Dist: torch
Requires-Dist: torchvision
Requires-Dist: numpy
Requires-Dist: pycocotools
